PySDM_examples/__init__.py
PySDM_examples/Abade_and_Albuquerque_2024/__init__.py
PySDM_examples/Abade_and_Albuquerque_2024/settings.py
PySDM_examples/Abade_and_Albuquerque_2024/simulation.py
PySDM_examples/Abdul_Razzak_Ghan_2000/__init__.py
PySDM_examples/Abdul_Razzak_Ghan_2000/aerosol.py
PySDM_examples/Abdul_Razzak_Ghan_2000/data_from_ARG2000_paper.py
PySDM_examples/Abdul_Razzak_Ghan_2000/data_from_CloudMicrophysics_ARG.py
PySDM_examples/Abdul_Razzak_Ghan_2000/run_ARG_parcel.py
PySDM_examples/Alpert_and_Knopf_2016/__init__.py
PySDM_examples/Alpert_and_Knopf_2016/simulation.py
PySDM_examples/Alpert_and_Knopf_2016/table.py
PySDM_examples/Alpert_and_Knopf_2016/table_1.py
PySDM_examples/Alpert_and_Knopf_2016/table_2.py
PySDM_examples/Arabas_and_Shima_2017/__init__.py
PySDM_examples/Arabas_and_Shima_2017/example.py
PySDM_examples/Arabas_and_Shima_2017/settings.py
PySDM_examples/Arabas_and_Shima_2017/simulation.py
PySDM_examples/Arabas_et_al_2015/__init__.py
PySDM_examples/Arabas_et_al_2015/example.py
PySDM_examples/Arabas_et_al_2015/example_benchmark.py
PySDM_examples/Arabas_et_al_2015/settings.py
PySDM_examples/Arabas_et_al_2015/spin_up.py
PySDM_examples/Arabas_et_al_2025/__init__.py
PySDM_examples/Arabas_et_al_2025/commons.py
PySDM_examples/Arabas_et_al_2025/curved_text.py
PySDM_examples/Arabas_et_al_2025/frozen_fraction.py
PySDM_examples/Arabas_et_al_2025/make_particulator.py
PySDM_examples/Arabas_et_al_2025/plots.py
PySDM_examples/Arabas_et_al_2025/run_simulation.py
PySDM_examples/Bartman_2020_MasterThesis/__init__.py
PySDM_examples/Bartman_2020_MasterThesis/fig_4_adaptive_sdm.py
PySDM_examples/Bartman_2020_MasterThesis/fig_5_SCIPY_VS_ADAPTIVE.py
PySDM_examples/Bartman_et_al_2021/__init__.py
PySDM_examples/Bartman_et_al_2021/label.py
PySDM_examples/Berry_1967/__init__.py
PySDM_examples/Berry_1967/example.py
PySDM_examples/Berry_1967/example_fig_6.py
PySDM_examples/Berry_1967/settings.py
PySDM_examples/Berry_1967/spectrum_plotter.py
pysdm_examples-2.131.dist-info/METADATA
pysdm_examples-2.131.dist-info/WHEEL
pysdm_examples-2.131.dist-info/top_level.txt
pysdm_examples-2.131.dist-info/RECORD
