Metadata-Version: 2.4
Name: pysdm-examples
Version: 2.131
Summary: PySDM usage examples reproducing results from literature and depicting how to use PySDM from Python Jupyter notebooks
Home-page: https://github.com/open-atmos/PySDM
Author: https://github.com/open-atmos/PySDM/graphs/contributors
Author-email: sylwester.arabas@agh.edu.pl
License: GPL-3.0
Project-URL: Tracker, https://github.com/open-atmos/PySDM/issues
Project-URL: Documentation, https://open-atmos.github.io/PySDM/PySDM_examples
Project-URL: Source, https://github.com/open-atmos/PySDM/tree/main/examples
Requires-Dist: PySDM
Requires-Dist: PyMPDATA
Requires-Dist: open-atmos-jupyter-utils
Requires-Dist: pystrict
Requires-Dist: matplotlib
Requires-Dist: Pillow
Requires-Dist: joblib
Requires-Dist: ipywidgets
Requires-Dist: seaborn
Requires-Dist: numdifftools
Requires-Dist: vtk
Provides-Extra: tests
Requires-Dist: pytest; extra == "tests"
Requires-Dist: nbconvert; extra == "tests"
Dynamic: author
Dynamic: author-email
Dynamic: description
Dynamic: description-content-type
Dynamic: home-page
Dynamic: license
Dynamic: project-url
Dynamic: provides-extra
Dynamic: requires-dist
Dynamic: summary
